{
  "user_profile": {
    "name": "River",
    "age": 21,
    "gender": "Non Binary",
    "other_gender": "",
    "orientation": "All",
    "goal": "To experience sensual control.",
    "weight_kg": 60,
    "height_cm": 172,
    "traits": "Analytical, sensual, deep thinker.",
    "kinks_fetishes": "Verbal submission, edge play, gentle force.",
    "limits": "No public play or degradation.",
    "content_settings": "Respect My Limits, But Feel the Mood",
    "content_types": [
      "friendship",
      "power_play",
      "body_exploration"
    ]
  },
  "ai_profile": {
    "voice_preference": "Male",
    "vibe": "🎲 Not sure — surprise me gently"
  }
}